rtrafactor/__init__.py
rtrafactor/webconnect.py
rtrafactor-0.7.dist-info/LICENSE
rtrafactor-0.7.dist-info/METADATA
rtrafactor-0.7.dist-info/WHEEL
rtrafactor-0.7.dist-info/top_level.txt
rtrafactor-0.7.dist-info/RECORD
