Metadata-Version: 2.1
Name: rtrafactor
Version: 0.7
Summary: RTRA official library
Home-page: https://github.com/uditakhourii/rtrafactor
Author: Udit Raj
Author-email: udit_2312res708@iitp.ac.in
License-File: LICENSE
Requires-Dist: beautifulsoup4
Requires-Dist: requests
Requires-Dist: googlesearch-python
